{
  "job_id": "0010-gen-data-depth20-1M-smallbox",
  "snapshot_at": "2026-05-18T09:00:11+00:00",
  "started_at": "2026-05-12T15:33:12+00:00",
  "elapsed_seconds": 494819,
  "artefacts": [
    {
      "name": "shard-1.bin",
      "size_bytes": 9500008,
      "records": 250000
    },
    {
      "name": "shard-1.log",
      "size_bytes": 8492
    },
    {
      "name": "shard-1.result",
      "size_bytes": 9
    },
    {
      "name": "shard-2.bin",
      "size_bytes": 9500008,
      "records": 250000
    },
    {
      "name": "shard-2.log",
      "size_bytes": 8493
    },
    {
      "name": "shard-2.result",
      "size_bytes": 9
    },
    {
      "name": "shard-3.bin",
      "size_bytes": 9500008,
      "records": 250000
    },
    {
      "name": "shard-3.log",
      "size_bytes": 8539
    },
    {
      "name": "shard-3.result",
      "size_bytes": 9
    },
    {
      "name": "shard-4.bin",
      "size_bytes": 9472034,
      "records": 249263
    },
    {
      "name": "shard-4.log",
      "size_bytes": 8192
    }
  ],
  "ps_session": "    PID    PPID     ELAPSED %CPU %MEM COMMAND\n  53908       1  5-17:26:58  0.0  0.0 bash\n  53909   53908  5-17:26:58  0.0  0.0 bash\n  53964   53909  5-17:26:55  0.0  0.0 bash\n  53969   53964  5-17:26:55 99.8  0.2 jass\n"
}
